sequential_processor/seqy86.v
module alu(
    a,b,fun,out
);

    input [63:0] a,b;
    input [3:0] fun;
    wire [1:0] sel;
    wire addof1,addof2,subof1,subof2;
    assign sel=fun[1:0];
    output [63:0] out;
    wire [63:0] out1,out2,out3,out4,nega;
    fulladder32bit addition1(a[31:0],b[31:0],1'b0,out1[31:0],addof1);
    fulladder32bit addition2(a[63:32],b[63:32],addof1,out1[63:32],addof2);
    // inverse32bit binv(a,nega);
    notgate32bit anot1(a[31:0],nega[31:0]);
    notgate32bit anot2(a[63:32],nega[63:32]);
    fulladder32bit subtraction1(nega[31:0],b[31:0],1'b1,out2[31:0],subof1);
    fulladder32bit subtraction2(nega[63:32],b[63:32],subof1,out2[63:32],subof2);
    andgate32bit andition1(a[31:0],b[31:0],out3[31:0]);
    andgate32bit andition2(a[63:32],b[63:32],out3[63:32]);
    xorgate32bit xorition1(a[31:0],b[31:0],out4[31:0]);
    xorgate32bit xorition2(a[63:32],b[63:32],out4[63:32]);
    mux4way32bit m1(out1[31:0],out2[31:0],out3[31:0],out4[31:0],sel,out[31:0]);
    mux4way32bit m2(out1[63:32],out2[63:32],out3[63:32],out4[63:32],sel,out[63:32]);
endmodule

module processor();
    reg [63:0] pc;
    reg clk;
    integer k;
    // wire [63:0] newpc;
    reg [63:0] newpc;
    reg [79:0] instruction;
    reg [3:0] icode,ifun;
    reg [3:0] rA,rB;
    reg [63:0] valC,valP,valM,valE;
    reg need_regids,need_valC;
    reg [3:0] dstE,dstM,srcA,srcB;
    reg [63:0] valA,valB;
    reg [63:0] aluA,aluB;
    reg [3:0] alufun;
    reg sf,of,zf;
    reg set_cc,Cnd;
    reg read,write;
    reg [63:0] mem_addr,mem_data;
    reg [79:0] ins_mem[1023:0];
    reg signed [63:0] reg_mem[15:0];
    reg signed [63:0] ram_mem[1023:0];
    wire signed [63:0] rax;
    wire signed [63:0] rcx;
    wire signed [63:0] rdx;
    wire signed [63:0] rbx;
    wire signed [63:0] RSP;

    // icode
    parameter halt =4'h0 ;
    parameter nop =4'h1 ;
    parameter rrmovq =4'h2 ;
    parameter irmovq =4'h3 ;
    parameter rmmovq =4'h4 ;
    parameter mrmovq =4'h5 ;
    parameter opq =4'h6 ;
    parameter jxx =4'h7;
    parameter call =4'h8 ;
    parameter ret =4'h9 ;
    parameter pushq =4'hA ;
    parameter popq =4'hB ;

    // ifun
    parameter ADD = 4'h0;
    parameter SUB = 4'h1;
    parameter AND = 4'h2;
    parameter XOR = 4'h3;

    // Branch Conditions
    parameter C_YES = 4'h0;
    parameter C_LE = 4'h1;
    parameter C_L = 4'h2;
    parameter C_E = 4'h3;
    parameter C_NE = 4'h4;
    parameter C_GE = 4'h5;
    parameter C_G = 4'h6;

    // Registers
    parameter rsp = 4'h4 ;
    parameter rnone =4'hF ;
    //fetch stage

    //instruction memory. The reason all of this had to be put together was in the always block everthing is executed sequentially one by one
    always @(posedge clk)
    begin
        pc=newpc;
        instruction=ins_mem[pc];
        // $display("time=%g,clk=%b,%h",$time,clk,instruction);
        
        //Icode and Ifun
        icode=instruction[7:4];
        ifun =instruction[3:0];

        // need registers and valC
        need_regids=(icode==rrmovq | icode==opq | icode==pushq |icode==popq | icode==irmovq | icode===rmmovq | icode==mrmovq)?1'b1:1'b0;

        //register A and register B and valC
        rA=need_regids?instruction[15:12]:rnone;
        rB=need_regids?instruction[11:8]:rnone;
        valC=need_regids?instruction[79:16]:instruction[71:8];

        //to implement the halt condition I just make the valP some arbitrary number. For the nop I just need to increment the pc and everything will be rnone and nothing will be written.
        //ValP -incrementing the pointer
        valP=(icode==halt)?64'h101000:(pc+64'b1);

        //SrcA
        srcA=(icode==rrmovq | icode==rmmovq | icode==opq | icode==pushq)?rA:(icode==popq | icode==ret)?rsp:rnone;

        //SrcB
        srcB=(icode==opq | icode==rmmovq | icode==mrmovq)?rB:(icode==pushq | icode==popq | icode==call | icode==ret)?rsp:rnone;

        //valA and valB
        valA=reg_mem[srcA];
        valB=reg_mem[srcB];

        //AluA
        aluA=(icode==rrmovq | icode==opq)?valA:(icode==irmovq | icode==rmmovq | icode==mrmovq)?valC:(icode==call | icode==pushq)?-64'h1:64'h1;

        //AluB
        aluB=(icode==opq | icode==rmmovq | icode==mrmovq | icode==pushq | icode==popq | icode==call | icode==ret)?valB:(icode==rrmovq | icode==irmovq)?64'b0:64'b0;

        //alufun
        alufun=(icode==opq)?ifun:ADD;

        //ALU-ValE
        valE=   (alufun == SUB) ? aluB-aluA:(alufun == AND) ? aluA & aluB:(alufun == XOR) ? (aluA ^ aluB):(aluA+aluB);
        // alu cpu(aluA,aluB,alufun,valE);
        //ALU-set_cc
        set_cc=(icode==opq)?1'b1:1'b0;

        //ALU-condition codes
        if(set_cc==1'b1)
        begin
        zf = (valE == 64'b0); // ZF
        sf = valE[63]; // SF
        of = (alufun == ADD) ? (aluA[63] == aluB[63]) & (aluA[63] != valE[63]) :
                        alufun == SUB ? (~aluA[63] == aluB[63]) & (aluB[63] != valE[63]) :
                        1'b0; // OF
        end

        //ALU-Cnd
        Cnd= ((ifun == C_YES) |
                (ifun == C_LE & ((sf^of)|zf)) | 
                (ifun == C_L & (sf^of)) |
                (ifun == C_E & zf) | 
                (ifun == C_NE & ~zf) | 
                (ifun == C_GE & (~sf^of)) | 
                (ifun == C_G & (~sf^of)&~zf)); 

        // Memory Stage 

        //Assigning the memory address
        mem_addr=(icode==rmmovq | icode==pushq | icode==call | icode==mrmovq)?valE:(icode==popq | icode==ret)?valA:64'h0;
        //Assigning the data in case of read
        mem_data=(icode==rmmovq | icode==pushq )?valA:(icode==call)?valP:64'b0;
        //Assigning the read control
        read=(icode==mrmovq | icode==popq | icode==ret)?1'b1:1'b0;
        //Assigning the write control
        write=(icode==rmmovq | icode==pushq | icode==call)?1'b1:1'b0;
        //Ram Module
    
        //read
        valM=(read==1'b1)?ram_mem[mem_addr]:64'b0;
        

        //DstE
        dstE=((Cnd & icode==rrmovq) | icode==irmovq | icode==opq)?rB:(icode==pushq | icode==popq | icode==call | icode==ret)?rsp:rnone;
        
        //DstM
        dstM=(icode==mrmovq | icode==popq)? rA:rnone;

        newpc = (icode==call | (icode==jxx & Cnd))?valC:(icode==ret)?valM:valP;
    end
    always @(negedge clk) begin
        reg_mem[dstE]=valE;
        reg_mem[dstM]=valM;
    end
    
    always @(negedge clk) begin
       if (write==1'b1)
        ram_mem[mem_addr]=mem_data;
    end

    assign rax=reg_mem[0];
    assign rcx=reg_mem[1];
    assign rdx=reg_mem[2];
    assign rbx=reg_mem[3];
    assign RSP=reg_mem[4];

    initial begin
        $readmemh("gcd_jmp_call.txt",ins_mem);
        $dumpfile("test.vcd");
        $dumpvars(0,processor);
        newpc=64'b0;
        Cnd=1'b0;
        clk=1'b0;
        //below is for the pc stage
        // $monitor("pc=%d,valP=%d,newpc=%d",pc,valP,newpc);
        //below is for the fetch block
        // $monitor("time=%g,clk=%b,icode=%h,ifun=%h,rA=%h,rB=%h,valC=%d",$time,clk,icode,ifun,rA,rB,valC);
        //below is for the decode block
        // $monitor("time=%g,clk=%b,srcA=%d,srcB=%d,valA=%d,valB=%d,dstE=%d,dstM=%d",$time,clk,srcA,srcB,valA,valB,dstE,dstM);
        //below is for the execute block
        // $monitor("time=%g,clk=%b,aluA=%d,aluB=%d,valE=%d,set_cc=%b,Cnd=%b",$time,clk,pc,aluA,aluB,valE,set_cc,Cnd);
        //below is for the memory block
        // $monitor("time=%g,clk=%b,aluA=%d,aluB=%d,valE=%d,mem_addr=%d,mem_data=%d,read=%b,write=%b,valM=%d",$time,clk,aluA,aluB,valE,mem_addr,mem_data,read,write,valM);
        #500
        begin
        $display("REGISTER\t\t\t\tRAM");
        for(k=0;k<16;k++)
            $display("%d:%d   %d",k,reg_mem[k],ram_mem[k]);
        $finish;
        end
    end
    always #1 clk=~clk;
endmodule

sequential_processor/test.vcd
$date
	Wed Mar 10 19:18:12 2021
$end
$version
	Icarus Verilog
$end
$timescale
	1s
$end
$scope module processor $end
$var wire 64 ! RSP [63:0] $end
$var wire 64 " rax [63:0] $end
$var wire 64 # rbx [63:0] $end
$var wire 64 $ rcx [63:0] $end
$var wire 64 % rdx [63:0] $end
$var reg 1 & Cnd $end
$var reg 64 ' aluA [63:0] $end
$var reg 64 ( aluB [63:0] $end
$var reg 4 ) alufun [3:0] $end
$var reg 1 * clk $end
$var reg 4 + dstE [3:0] $end
$var reg 4 , dstM [3:0] $end
$var reg 4 - icode [3:0] $end
$var reg 4 . ifun [3:0] $end
$var reg 80 / instruction [79:0] $end
$var reg 64 0 mem_addr [63:0] $end
$var reg 64 1 mem_data [63:0] $end
$var reg 1 2 need_regids $end
$var reg 64 3 newpc [63:0] $end
$var reg 1 4 of $end
$var reg 64 5 pc [63:0] $end
$var reg 4 6 rA [3:0] $end
$var reg 4 7 rB [3:0] $end
$var reg 1 8 read $end
$var reg 1 9 set_cc $end
$var reg 1 : sf $end
$var reg 4 ; srcA [3:0] $end
$var reg 4 < srcB [3:0] $end
$var reg 64 = valA [63:0] $end
$var reg 64 > valB [63:0] $end
$var reg 64 ? valC [63:0] $end
$var reg 64 @ valE [63:0] $end
$var reg 64 A valM [63:0] $end
$var reg 64 B valP [63:0] $end
$var reg 1 C write $end
$var reg 1 D zf $end
$var integer 32 E k [31:0] $end
$upscope $end
$enddefinitions $end
#0
$dumpvars
bx E
xD
xC
bx B
bx A
bx @
bx ?
bx >
bx =
bx <
bx ;
x:
x9
x8
bx 7
bx 6
bx 5
x4
b0 3
x2
bx 1
bx 0
bx /
bx .
bx -
bx ,
bx +
0*
bx )
bx (
bx '
0&
bx %
bx $
bx #
bx "
bx !
$end
#1
b1 3
b1111 ,
b100 +
b0 A
0C
08
b0 1
b0 0
1&
09
b1111100111 @
b0 )
b0 (
b1111100111 '
b1111 <
b1111 ;
b1 B
b1111100111 ?
b100 7
b1111 6
12
b0 .
b11 -
b11111001111111010000110000 /
b0 5
1*
#2
b1111100111 !
0*
#3
b1101 3
1C
b10 1
b1111100110 0
b1111100110 @
b1111100111 (
b1111111111111111111111111111111111111111111111111111111111111111 '
b1111100111 >
b0 =
b100 <
b10 B
b1101 ?
b1111 7
02
b1000 -
b110110000000 /
b1 5
1*
#4
b1111100110 !
0*
#5
b1110 3
b0 +
0C
b0 1
b0 0
b1001 @
b0 (
b1001 '
b0 >
b1111 <
b1110 B
b1001 ?
b0 7
12
b11 -
b10011111000000110000 /
b1101 5
1*
#6
b1001 "
0*
#7
b1111 3
b1 +
b101 @
b101 '
b1111 B
b101 ?
b1 7
b1011111000100110000 /
b1110 5
1*
#8
b101 $
0*
#9
b11 3
b100 +
1C
b10000 1
b1111100101 0
b1111100101 @
b1111100110 (
b1111111111111111111111111111111111111111111111111111111111111111 '
b1111100110 >
b100 <
b10000 B
b11 ?
b1111 7
02
b1000 -
b1110000000 /
b1111 5
1*
#10
b1111100101 !
0*
#11
b100 3
b10 +
0C
b0 1
b0 0
b101 @
b0 (
b101 '
b0 >
b101 =
b1111 <
b1 ;
b100 B
b0 ?
b10 7
b1 6
12
b10 -
b1001000100000 /
b11 5
1*
#12
b101 %
0*
#13
b101 3
04
1:
0D
19
b1111111111111111111111111111111111111111111111111111111111111100 @
b1 )
b101 (
b1001 '
b101 >
b1001 =
b10 <
b0 ;
b101 B
b0 6
b1 .
b110 -
b1001100001 /
b100 5
1*
#14
b1111111111111111111111111111111111111111111111111111111111111100 %
0*
#15
b110 3
b1111 +
0&
09
b1 @
b0 )
b0 (
b1 '
b0 >
b0 =
b1111 <
b1111 ;
b110 B
b1011 ?
b1111 7
b1111 6
02
b11 .
b111 -
b101101110011 /
b101 5
1*
#16
0*
#17
b1001 3
1&
b111 B
b1001 ?
b10 .
b100101110010 /
b110 5
1*
#18
0*
#19
b1010 3
b0 +
0&
0:
19
b100 @
b1 )
b1001 (
b101 '
b1001 >
b101 =
b0 <
b1 ;
b1010 B
b0 ?
b0 7
b1 6
12
b1 .
b110 -
b1000001100001 /
b1001 5
1*
#20
b100 "
0*
#21
b11 3
b1111 +
1&
09
b1 @
b0 )
b0 (
b1 '
b0 >
b0 =
b1111 <
b1111 ;
b1011 B
b11 ?
b1111 7
b1111 6
02
b0 .
b111 -
b1101110000 /
b1010 5
1*
#22
0*
#23
b100 3
b10 +
b101 @
b101 '
b101 =
b1 ;
b100 B
b0 ?
b10 7
b1 6
12
b10 -
b1001000100000 /
b11 5
1*
#24
b101 %
0*
#25
b101 3
0&
19
b1 @
b1 )
b101 (
b100 '
b101 >
b100 =
b10 <
b0 ;
b101 B
b0 6
b1 .
b110 -
b1001100001 /
b100 5
1*
#26
b1 %
0*
#27
b110 3
b1111 +
09
b0 )
b0 (
b1 '
b0 >
b0 =
b1111 <
b1111 ;
b110 B
b1011 ?
b1111 7
b1111 6
02
b11 .
b111 -
b101101110011 /
b101 5
1*
#28
0*
#29
b111 3
b111 B
b1001 ?
b10 .
b100101110010 /
b110 5
1*
#30
0*
#31
b1000 3
b1 +
19
b1 )
b101 (
b100 '
b101 >
b100 =
b1 <
b0 ;
b1000 B
b0 ?
b1 7
b0 6
12
b1 .
b110 -
b101100001 /
b111 5
1*
#32
b1 $
0*
#33
b11 3
b1111 +
1&
09
b0 )
b0 (
b1 '
b0 >
b0 =
b1111 <
b1111 ;
b1001 B
b11 ?
b1111 7
b1111 6
02
b0 .
b111 -
b1101110000 /
b1000 5
1*
#34
0*
#35
b100 3
b10 +
b1 =
b1 ;
b100 B
b0 ?
b10 7
b1 6
12
b10 -
b1001000100000 /
b11 5
1*
#36
0*
#37
b101 3
1:
19
b1111111111111111111111111111111111111111111111111111111111111101 @
b1 )
b1 (
b100 '
b1 >
b100 =
b10 <
b0 ;
b101 B
b0 6
b1 .
b110 -
b1001100001 /
b100 5
1*
#38
b1111111111111111111111111111111111111111111111111111111111111101 %
0*
#39
b110 3
b1111 +
0&
09
b1 @
b0 )
b0 (
b1 '
b0 >
b0 =
b1111 <
b1111 ;
b110 B
b1011 ?
b1111 7
b1111 6
02
b11 .
b111 -
b101101110011 /
b101 5
1*
#40
0*
#41
b1001 3
1&
b111 B
b1001 ?
b10 .
b100101110010 /
b110 5
1*
#42
0*
#43
b1010 3
b0 +
0&
0:
19
b11 @
b1 )
b100 (
b100 >
b1 =
b0 <
b1 ;
b1010 B
b0 ?
b0 7
b1 6
12
b1 .
b110 -
b1000001100001 /
b1001 5
1*
#44
b11 "
0*
#45
b11 3
b1111 +
1&
09
b1 @
b0 )
b0 (
b0 >
b0 =
b1111 <
b1111 ;
b1011 B
b11 ?
b1111 7
b1111 6
02
b0 .
b111 -
b1101110000 /
b1010 5
1*
#46
0*
#47
b100 3
b10 +
b1 =
b1 ;
b100 B
b0 ?
b10 7
b1 6
12
b10 -
b1001000100000 /
b11 5
1*
#48
b1 %
0*
#49
b101 3
1:
19
b1111111111111111111111111111111111111111111111111111111111111110 @
b1 )
b1 (
b11 '
b1 >
b11 =
b10 <
b0 ;
b101 B
b0 6
b1 .
b110 -
b1001100001 /
b100 5
1*
#50
b1111111111111111111111111111111111111111111111111111111111111110 %
0*
#51
b110 3
b1111 +
0&
09
b1 @
b0 )
b0 (
b1 '
b0 >
b0 =
b1111 <
b1111 ;
b110 B
b1011 ?
b1111 7
b1111 6
02
b11 .
b111 -
b101101110011 /
b101 5
1*
#52
0*
#53
b1001 3
1&
b111 B
b1001 ?
b10 .
b100101110010 /
b110 5
1*
#54
0*
#55
b1010 3
b0 +
0&
0:
19
b10 @
b1 )
b11 (
b11 >
b1 =
b0 <
b1 ;
b1010 B
b0 ?
b0 7
b1 6
12
b1 .
b110 -
b1000001100001 /
b1001 5
1*
#56
b10 "
0*
#57
b11 3
b1111 +
1&
09
b1 @
b0 )
b0 (
b0 >
b0 =
b1111 <
b1111 ;
b1011 B
b11 ?
b1111 7
b1111 6
02
b0 .
b111 -
b1101110000 /
b1010 5
1*
#58
0*
#59
b100 3
b10 +
b1 =
b1 ;
b100 B
b0 ?
b10 7
b1 6
12
b10 -
b1001000100000 /
b11 5
1*
#60
b1 %
0*
#61
b101 3
1:
19
b1111111111111111111111111111111111111111111111111111111111111111 @
b1 )
b1 (
b10 '
b1 >
b10 =
b10 <
b0 ;
b101 B
b0 6
b1 .
b110 -
b1001100001 /
b100 5
1*
#62
b1111111111111111111111111111111111111111111111111111111111111111 %
0*
#63
b110 3
b1111 +
0&
09
b1 @
b0 )
b0 (
b1 '
b0 >
b0 =
b1111 <
b1111 ;
b110 B
b1011 ?
b1111 7
b1111 6
02
b11 .
b111 -
b101101110011 /
b101 5
1*
#64
0*
#65
b1001 3
1&
b111 B
b1001 ?
b10 .
b100101110010 /
b110 5
1*
#66
0*
#67
b1010 3
b0 +
0&
0:
19
b1 )
b10 (
b10 >
b1 =
b0 <
b1 ;
b1010 B
b0 ?
b0 7
b1 6
12
b1 .
b110 -
b1000001100001 /
b1001 5
1*
#68
b1 "
0*
#69
b11 3
b1111 +
1&
09
b0 )
b0 (
b0 >
b0 =
b1111 <
b1111 ;
b1011 B
b11 ?
b1111 7
b1111 6
02
b0 .
b111 -
b1101110000 /
b1010 5
1*
#70
0*
#71
b100 3
b10 +
b1 =
b1 ;
b100 B
b0 ?
b10 7
b1 6
12
b10 -
b1001000100000 /
b11 5
1*
#72
b1 %
0*
#73
b101 3
1D
19
b0 @
b1 )
b1 (
b1 >
b10 <
b0 ;
b101 B
b0 6
b1 .
b110 -
b1001100001 /
b100 5
1*
#74
b0 %
0*
#75
b1011 3
b1111 +
09
b1 @
b0 )
b0 (
b0 >
b0 =
b1111 <
b1111 ;
b110 B
b1011 ?
b1111 7
b1111 6
02
b11 .
b111 -
b101101110011 /
b101 5
1*
#76
0*
#77
b1100 3
b11 +
b1 =
b0 ;
b1100 B
b0 ?
b11 7
b0 6
12
b0 .
b10 -
b1100100000 /
b1011 5
1*
#78
b1 #
0*
#79
b10000 3
b100 +
b10000 A
18
b1111100101 0
b1111100110 @
b1111100101 (
b1111100101 >
b1111100101 =
b100 <
b100 ;
b1101 B
b1111 7
b1111 6
02
b1001 -
b10010000 /
b1100 5
1*
#80
b1111100110 !
0*
#81
b10 3
b10 A
b1111100110 0
b1111100111 @
b1111100110 (
b1111100110 >
b1111100110 =
b10001 B
b10000 5
1*
#82
b1111100111 !
0*
#83
b100000001000000000000 3
b1111 +
b0 A
08
b0 0
b1 @
b0 (
b10 >
b10 =
b1111 <
b1111 ;
b100000001000000000000 B
b0 -
b0 /
b10 5
1*
#84
0*
#85
bx 3
bx ,
bx +
bx A
xC
x8
bx 1
bx 0
x&
x9
bx @
bx )
bx (
bx '
bx >
bx =
bx <
bx ;
b10000000100000000000x B
bx ?
bx 7
bx 6
x2
bx .
bx -
bx /
b100000001000000000000 5
1*
#86
0*
#87
bx B
bx 5
1*
